main.py
collegedsp-0.0.1.dist-info/LICENSE
collegedsp-0.0.1.dist-info/METADATA
collegedsp-0.0.1.dist-info/WHEEL
collegedsp-0.0.1.dist-info/top_level.txt
collegedsp-0.0.1.dist-info/RECORD
